CHANGES.txt
DEPENDENCES.txt
README.txt
setup.py
src/ng/__init__.py
src/ng.app.rss.egg-info/PKG-INFO
src/ng.app.rss.egg-info/SOURCES.txt
src/ng.app.rss.egg-info/dependency_links.txt
src/ng.app.rss.egg-info/namespace_packages.txt
src/ng.app.rss.egg-info/not-zip-safe
src/ng.app.rss.egg-info/requires.txt
src/ng.app.rss.egg-info/top_level.txt
src/ng/app/__init__.py
src/ng/app/rss/__init__.py
src/ng/app/rss/configure.zcml
src/ng/app/rss/interfaces.py
src/ng/app/rss/ng.app.rss.txt
src/ng/app/rss/rss.py
src/ng/app/rss/rssadapter.py
src/ng/app/rss/zdc2rssentryadapter.py
src/ng/app/rss/browser/__init__.py
src/ng/app/rss/browser/configure.zcml
src/ng/app/rss/etc/ng.app.rss-configure.zcml
src/ng/app/rss/rssview/__init__.py
src/ng/app/rss/rssview/configure.zcml
src/ng/app/rss/rssview/rssview.pt
src/ng/app/rss/rssview/rssview.py
